pybuilder_pylint_extended/__init__.py
pybuilder_pylint_extended/python_plugin_helper.py
pybuilder_pylint_extended/version.py
pybuilder_pylint_extended-1.1.0.dist-info/DESCRIPTION.rst
pybuilder_pylint_extended-1.1.0.dist-info/METADATA
pybuilder_pylint_extended-1.1.0.dist-info/RECORD
pybuilder_pylint_extended-1.1.0.dist-info/WHEEL
pybuilder_pylint_extended-1.1.0.dist-info/metadata.json
pybuilder_pylint_extended-1.1.0.dist-info/namespace_packages.txt
pybuilder_pylint_extended-1.1.0.dist-info/top_level.txt
pybuilder_pylint_extended-1.1.0.dist-info/zip-safe
